{"organization": {"id": 251191386, "ein": 251191386, "name": "Mutual Aid Ambulance Service Inc", "careofname": null, "address": "PO BOX 350", "city": "Greensburg", "state": "PA", "zipcode": "15601-0350", "exemption_number": 0, "subsection_code": 3, "affiliation_code": 3, "classification_codes": "1200", "ruling_date": "1984-12-01", "deductibility_code": 1, "foundation_code": 16, "activity_codes": "158179149", "organization_code": 1, "exempt_organization_status_code": 1, "tax_period": "2024-12-01", "asset_code": 8, "income_code": 8, "filing_requirement_code": 1, "pf_filing_requirement_code": 0, "accounting_period": 12, "asset_amount": 40859490, "income_amount": 43742998, "revenue_amount": 23453339, "ntee_code": "E63Z", "sort_name": null, "created_at": "2023-05-09T20:27:23.315Z", "updated_at": "2026-01-22T18:48:30.146Z", "data_source": "current_2026_01_22", "have_extracts": null, "have_pdfs": null, "latest_object_id": "202523219349302677"}, "filings_with_data": [{"tax_prd": 202312, "tax_prd_yr": 2023, "formtype": 0, "pdf_url": null, "updated": "2025-08-05T16:08:30.469Z", "totrevenue": 25016807, "totfuncexpns": 25987116, "totassetsend": 42748305, "totliabend": 9446462, "pct_compnsatncurrofcr": 0.0, "tax_pd": null, "subseccd": 3, "unrelbusinccd": "Y", "initiationfees": 0, "grsrcptspublicuse": 0, "grsincmembers": 0, "grsincother": 0, "totcntrbgfts": 4512820, "totprgmrevnue": 19150590, "invstmntinc": 866523, "txexmptbndsproceeds": 0, "royaltsinc": 0, "grsrntsreal": 3000, "grsrntsprsnl": 0, "rntlexpnsreal": 0, "rntlexpnsprsnl": 0, "rntlincreal": 3000, "rntlincprsnl": 0, "netrntlinc": 3000, "grsalesecur": 25460889, "grsalesothr": 99500, "cstbasisecur": 25053444, "cstbasisothr": 111212, "gnlsecur": 407445, "gnlsothr": -11712, "netgnls": 395733, "grsincfndrsng": 36742, "lessdirfndrsng": 32533, "netincfndrsng": 4209, "grsincgaming": 0, "lessdirgaming": 0, "netincgaming": 0, "grsalesinvent": 0, "lesscstofgoods": 0, "netincsales": 0, "miscrevtot11e": 83932, "compnsatncurrofcr": 155104, "othrsalwages": 13841851, "payrolltx": 1052954, "profndraising": 0, "txexmptbndsend": 0, "secrdmrtgsend": 2054891, "unsecurednotesend": 0, "retainedearnend": 0, "totnetassetend": 33301843, "nonpfrea": "9", "gftgrntsrcvd170": 0, "txrevnuelevied170": 0, "srvcsval170": 0, "grsinc170": 0, "grsrcptsrelated170": 0, "totgftgrntrcvd509": 10273157, "grsrcptsadmissn509": 76702708, "txrevnuelevied509": 0, "srvcsval509": 0, "subtotsuppinc509": 4297069, "totsupp509": 95140883, "ein": 251191386}, {"tax_prd": 202212, "tax_prd_yr": 2022, "formtype": 0, "pdf_url": "https://projects.propublica.org/nonprofits/download-filing?path=download990pdf_01_2024_prefixes_24-26%2F251191386_202212_990_2024010922193975.pdf", "updated": "2024-08-28T20:07:56.162Z", "totrevenue": 20741985, "totfuncexpns": 26648495, "totassetsend": 38247746, "totliabend": 13149305, "pct_compnsatncurrofcr": 0.0, "tax_pd": null, "subseccd": 3, "unrelbusinccd": "N", "initiationfees": 0, "grsrcptspublicuse": 0, "grsincmembers": 0, "grsincother": 0, "totcntrbgfts": 477354, "totprgmrevnue": 19654091, "invstmntinc": 610540, "txexmptbndsproceeds": 0, "royaltsinc": 0, "grsrntsreal": 0, "grsrntsprsnl": 0, "rntlexpnsreal": 0, "rntlexpnsprsnl": 0, "rntlincreal": 0, "rntlincprsnl": 0, "netrntlinc": 0, "grsalesecur": 0, "grsalesothr": 0, "cstbasisecur": 0, "cstbasisothr": 0, "gnlsecur": 0, "gnlsothr": 0, "netgnls": 0, "grsincfndrsng": 0, "lessdirfndrsng": 0, "netincfndrsng": 0, "grsincgaming": 0, "lessdirgaming": 0, "netincgaming": 0, "grsalesinvent": 0, "lesscstofgoods": 0, "netincsales": 0, "miscrevtot11e": 0, "compnsatncurrofcr": 256366, "othrsalwages": 14237973, "payrolltx": 1096601, "profndraising": 0, "txexmptbndsend": 0, "secrdmrtgsend": 0, "unsecurednotesend": 0, "retainedearnend": 0, "totnetassetend": 25098441, "nonpfrea": "9", "gftgrntsrcvd170": 0, "txrevnuelevied170": 0, "srvcsval170": 0, "grsinc170": 0, "grsrcptsrelated170": 0, "totgftgrntrcvd509": 3923300, "grsrcptsadmissn509": 68752497, "txrevnuelevied509": 0, "srvcsval509": 0, "subtotsuppinc509": 4602128, "totsupp509": 81553632, "ein": 251191386}, {"tax_prd": 202112, "tax_prd_yr": 2021, "formtype": 0, "pdf_url": "https://projects.propublica.org/nonprofits/download-filing?path=download990pdf_01_2024_prefixes_24-26%2F251191386_202112_990_2024010322167057.pdf", "updated": "2023-08-07T19:36:58.497Z", "totrevenue": 14449938, "totfuncexpns": 19615058, "totassetsend": 44444924, "totliabend": 11448519, "pct_compnsatncurrofcr": 0.0, "tax_pd": null, "subseccd": 3, "unrelbusinccd": "N", "initiationfees": 0, "grsrcptspublicuse": 0, "grsincmembers": 0, "grsincother": 0, "totcntrbgfts": 104529, "totprgmrevnue": 13412741, "invstmntinc": 887973, "txexmptbndsproceeds": 0, "royaltsinc": 0, "grsrntsreal": 0, "grsrntsprsnl": 0, "rntlexpnsreal": 0, "rntlexpnsprsnl": 0, "rntlincreal": 0, "rntlincprsnl": 0, "netrntlinc": 0, "grsalesecur": 0, "grsalesothr": 72000, "cstbasisecur": 0, "cstbasisothr": 27305, "gnlsecur": 0, "gnlsothr": 44695, "netgnls": 44695, "grsincfndrsng": 0, "lessdirfndrsng": 0, "netincfndrsng": 0, "grsincgaming": 0, "lessdirgaming": 0, "netincgaming": 0, "grsalesinvent": 0, "lesscstofgoods": 0, "netincsales": 0, "miscrevtot11e": 0, "compnsatncurrofcr": 131357, "othrsalwages": 10561271, "payrolltx": 812014, "profndraising": 0, "txexmptbndsend": 0, "secrdmrtgsend": 0, "unsecurednotesend": 0, "retainedearnend": 0, "totnetassetend": 32996405, "nonpfrea": "09", "gftgrntsrcvd170": 0, "txrevnuelevied170": 0, "srvcsval170": 0, "grsinc170": 0, "grsrcptsrelated170": 0, "totgftgrntrcvd509": 3480026, "grsrcptsadmissn509": 64554919, "txrevnuelevied509": 0, "srvcsval509": 0, "subtotsuppinc509": 4557622, "totsupp509": 76025403, "ein": 251191386}, {"tax_prd": 202103, "tax_prd_yr": 2021, "formtype": 0, "pdf_url": "https://projects.propublica.org/nonprofits/download-filing?path=IRS%2F251191386_202103_990_2022022819670847.pdf", "updated": "2023-08-07T19:36:58.497Z", "totrevenue": 15155292, "totfuncexpns": 23843540, "totassetsend": 49278643, "totliabend": 10436652, "pct_compnsatncurrofcr": 0.0, "tax_pd": null, "subseccd": 3, "unrelbusinccd": "N", "initiationfees": 0, "grsrcptspublicuse": 0, "grsincmembers": 0, "grsincother": 0, "totcntrbgfts": 127617, "totprgmrevnue": 14409251, "invstmntinc": 612974, "txexmptbndsproceeds": 0, "royaltsinc": 0, "grsrntsreal": 0, "grsrntsprsnl": 0, "rntlexpnsreal": 0, "rntlexpnsprsnl": 0, "rntlincreal": 0, "rntlincprsnl": 0, "netrntlinc": 0, "grsalesecur": 0, "grsalesothr": 5450, "cstbasisecur": 0, "cstbasisothr": 0, "gnlsecur": 0, "gnlsothr": 5450, "netgnls": 5450, "grsincfndrsng": 0, "lessdirfndrsng": 0, "netincfndrsng": 0, "grsincgaming": 0, "lessdirgaming": 0, "netincgaming": 0, "grsalesinvent": 0, "lesscstofgoods": 0, "netincsales": 0, "miscrevtot11e": 0, "compnsatncurrofcr": 160697, "othrsalwages": 13334739, "payrolltx": 1098751, "profndraising": 0, "txexmptbndsend": 0, "secrdmrtgsend": 0, "unsecurednotesend": 0, "retainedearnend": 0, "totnetassetend": 38841991, "nonpfrea": "09", "gftgrntsrcvd170": 0, "txrevnuelevied170": 0, "srvcsval170": 0, "grsinc170": 0, "grsrcptsrelated170": 0, "totgftgrntrcvd509": 3706398, "grsrcptsadmissn509": 65634353, "txrevnuelevied509": 0, "srvcsval509": 0, "subtotsuppinc509": 4071149, "totsupp509": 76447744, "ein": 251191386}, {"tax_prd": 202003, "tax_prd_yr": 2020, "formtype": 0, "pdf_url": "https://projects.propublica.org/nonprofits/download-filing?path=04_2021_prefixes_23-25%2F251191386_202003_990_2021041217925183.pdf", "updated": "2022-07-01T20:29:01.813Z", "totrevenue": 14902156, "totfuncexpns": 18017344, "totassetsend": 55851806, "totliabend": 13845469, "pct_compnsatncurrofcr": 0.0, "tax_pd": null, "subseccd": 3, "unrelbusinccd": "N", "initiationfees": 0, "grsrcptspublicuse": 0, "grsincmembers": 0, "grsincother": 0, "totcntrbgfts": 99108, "totprgmrevnue": 13468892, "invstmntinc": 1316059, "txexmptbndsproceeds": 0, "royaltsinc": 0, "grsrntsreal": 0, "grsrntsprsnl": 0, "rntlexpnsreal": 0, "rntlexpnsprsnl": 0, "rntlincreal": 0, "rntlincprsnl": 0, "netrntlinc": 0, "grsalesecur": 0, "grsalesothr": 18097, "cstbasisecur": 0, "cstbasisothr": 0, "gnlsecur": 0, "gnlsothr": 18097, "netgnls": 18097, "grsincfndrsng": 0, "lessdirfndrsng": 0, "netincfndrsng": 0, "grsincgaming": 0, "lessdirgaming": 0, "netincgaming": 0, "grsalesinvent": 0, "lesscstofgoods": 0, "netincsales": 0, "miscrevtot11e": 0, "compnsatncurrofcr": 209869, "othrsalwages": 10710047, "payrolltx": 864658, "profndraising": 0, "txexmptbndsend": 0, "secrdmrtgsend": 0, "unsecurednotesend": 0, "retainedearnend": 0, "totnetassetend": 42006337, "nonpfrea": "9", "gftgrntsrcvd170": 0, "txrevnuelevied170": 0, "srvcsval170": 0, "grsinc170": 0, "grsrcptsrelated170": 0, "totgftgrntrcvd509": 3625317, "grsrcptsadmissn509": 64935081, "txrevnuelevied509": 0, "srvcsval509": 0, "subtotsuppinc509": 4024298, "totsupp509": 75376240, "ein": 251191386}, {"tax_prd": 201903, "tax_prd_yr": 2019, "formtype": 0, "pdf_url": "https://projects.propublica.org/nonprofits/download-filing?path=10_2019_prefixes_23-26%2F251191386_201903_990_2019103016798690.pdf", "updated": "2021-08-30T18:35:22.556Z", "totrevenue": 16304260, "totfuncexpns": 14414038, "totassetsend": 56968477, "totliabend": 5072674, "pct_compnsatncurrofcr": 0.0, "tax_pd": null, "subseccd": 3, "unrelbusinccd": "Y", "initiationfees": 0, "grsrcptspublicuse": 0, "grsincmembers": 0, "grsincother": 0, "totcntrbgfts": 112176, "totprgmrevnue": 15017502, "invstmntinc": 1174582, "txexmptbndsproceeds": 0, "royaltsinc": 0, "grsrntsreal": 0, "grsrntsprsnl": 0, "rntlexpnsreal": 0, "rntlexpnsprsnl": 0, "rntlincreal": 0, "rntlincprsnl": 0, "netrntlinc": 0, "grsalesecur": 0, "grsalesothr": 0, "cstbasisecur": 0, "cstbasisothr": 0, "gnlsecur": 0, "gnlsothr": 0, "netgnls": 0, "grsincfndrsng": 0, "lessdirfndrsng": 0, "netincfndrsng": 0, "grsincgaming": 0, "lessdirgaming": 0, "netincgaming": 0, "grsalesinvent": 0, "lesscstofgoods": 0, "netincsales": 0, "miscrevtot11e": 0, "compnsatncurrofcr": 221335, "othrsalwages": 8625814, "payrolltx": 706343, "profndraising": 0, "txexmptbndsend": 0, "secrdmrtgsend": 0, "unsecurednotesend": 0, "retainedearnend": 0, "totnetassetend": 51895803, "nonpfrea": "09", "gftgrntsrcvd170": 0, "txrevnuelevied170": 0, "srvcsval170": 0, "grsinc170": 0, "grsrcptsrelated170": 0, "totgftgrntrcvd509": 3630620, "grsrcptsadmissn509": 65492344, "txrevnuelevied509": 0, "srvcsval509": 0, "subtotsuppinc509": 3304607, "totsupp509": 74945951, "ein": 251191386}, {"tax_prd": 201803, "tax_prd_yr": 2018, "formtype": 0, "pdf_url": "https://projects.propublica.org/nonprofits/download-filing?path=10_2018_prefixes_23-26%2F251191386_201803_990_2018102515832075.pdf", "updated": "2019-10-15T18:04:25.478Z", "totrevenue": 15213758, "totfuncexpns": 13691751, "totassetsend": 54991726, "totliabend": 4123588, "pct_compnsatncurrofcr": 0.0, "tax_pd": null, "subseccd": 3, "unrelbusinccd": "Y", "initiationfees": 0, "grsrcptspublicuse": 0, "grsincmembers": 0, "grsincother": 0, "totcntrbgfts": 91941, "totprgmrevnue": 14564155, "invstmntinc": 566034, "txexmptbndsproceeds": 0, "royaltsinc": 0, "grsrntsreal": 0, "grsrntsprsnl": 0, "rntlexpnsreal": 0, "rntlexpnsprsnl": 0, "rntlincreal": 0, "rntlincprsnl": 0, "netrntlinc": 0, "grsalesecur": 0, "grsalesothr": 0, "cstbasisecur": 0, "cstbasisothr": 8372, "gnlsecur": 0, "gnlsothr": -8372, "netgnls": -8372, "grsincfndrsng": 0, "lessdirfndrsng": 0, "netincfndrsng": 0, "grsincgaming": 0, "lessdirgaming": 0, "netincgaming": 0, "grsalesinvent": 0, "lesscstofgoods": 0, "netincsales": 0, "miscrevtot11e": 0, "compnsatncurrofcr": 212895, "othrsalwages": 8329872, "payrolltx": 699722, "profndraising": 0, "txexmptbndsend": 0, "secrdmrtgsend": 0, "unsecurednotesend": 0, "retainedearnend": 0, "totnetassetend": 50868138, "nonpfrea": "9", "gftgrntsrcvd170": 0, "txrevnuelevied170": 0, "srvcsval170": 0, "grsinc170": 0, "grsrcptsrelated170": 0, "totgftgrntrcvd509": 3583439, "grsrcptsadmissn509": 64184879, "txrevnuelevied509": 0, "srvcsval509": 0, "subtotsuppinc509": 2765211, "totsupp509": 72862999, "ein": 251191386}, {"tax_prd": 201703, "tax_prd_yr": 2017, "formtype": 0, "pdf_url": "https://projects.propublica.org/nonprofits/download-filing?path=IRS%2F251191386_201703_990_2017110814938697.pdf", "updated": "2018-12-10T23:09:08.227Z", "totrevenue": 14872279, "totfuncexpns": 13694723, "totassetsend": 52741989, "totliabend": 3960569, "pct_compnsatncurrofcr": 0.0, "tax_pd": null, "subseccd": 3, "unrelbusinccd": "Y", "initiationfees": 0, "grsrcptspublicuse": 0, "grsincmembers": 0, "grsincother": 0, "totcntrbgfts": 136606, "totprgmrevnue": 14334173, "invstmntinc": 401500, "txexmptbndsproceeds": 0, "royaltsinc": 0, "grsrntsreal": 0, "grsrntsprsnl": 0, "rntlexpnsreal": 0, "rntlexpnsprsnl": 0, "rntlincreal": 0, "rntlincprsnl": 0, "netrntlinc": 0, "grsalesecur": 0, "grsalesothr": 0, "cstbasisecur": 0, "cstbasisothr": 0, "gnlsecur": 0, "gnlsothr": 0, "netgnls": 0, "grsincfndrsng": 0, "lessdirfndrsng": 0, "netincfndrsng": 0, "grsincgaming": 0, "lessdirgaming": 0, "netincgaming": 0, "grsalesinvent": 0, "lesscstofgoods": 0, "netincsales": 0, "miscrevtot11e": 0, "compnsatncurrofcr": 228846, "othrsalwages": 8235678, "payrolltx": 699467, "profndraising": 0, "txexmptbndsend": 0, "secrdmrtgsend": 0, "unsecurednotesend": 0, "retainedearnend": 0, "totnetassetend": 48781420, "nonpfrea": "9", "gftgrntsrcvd170": 0, "txrevnuelevied170": 0, "srvcsval170": 0, "grsinc170": 0, "grsrcptsrelated170": 0, "totgftgrntrcvd509": 3582259, "grsrcptsadmissn509": 63067695, "txrevnuelevied509": 0, "srvcsval509": 0, "subtotsuppinc509": 2849356, "totsupp509": 71655798, "ein": 251191386}, {"tax_prd": 201603, "tax_prd_yr": 2016, "formtype": 0, "pdf_url": "https://projects.propublica.org/nonprofits/download-filing?path=2017_01_EO%2F25-1191386_990_201603.pdf", "updated": "2017-06-30T00:35:55.427Z", "totrevenue": 14080258, "totfuncexpns": 13622220, "totassetsend": 51011714, "totliabend": 4967125, "pct_compnsatncurrofcr": 0.0, "tax_pd": null, "subseccd": 3, "unrelbusinccd": "N", "initiationfees": 0, "grsrcptspublicuse": 0, "grsincmembers": 0, "grsincother": 0, "totcntrbgfts": 64788, "totprgmrevnue": 13452877, "invstmntinc": 566123, "txexmptbndsproceeds": 0, "royaltsinc": 0, "grsrntsreal": 0, "grsrntsprsnl": 0, "rntlexpnsreal": 0, "rntlexpnsprsnl": 0, "rntlincreal": 0, "rntlincprsnl": 0, "netrntlinc": 0, "grsalesecur": 0, "grsalesothr": 0, "cstbasisecur": 0, "cstbasisothr": 3530, "gnlsecur": 0, "gnlsothr": -3530, "netgnls": -3530, "grsincfndrsng": 0, "lessdirfndrsng": 0, "netincfndrsng": 0, "grsincgaming": 0, "lessdirgaming": 0, "netincgaming": 0, "grsalesinvent": 0, "lesscstofgoods": 0, "netincsales": 0, "miscrevtot11e": 0, "compnsatncurrofcr": 249518, "othrsalwages": 8265131, "payrolltx": 679663, "profndraising": 0, "txexmptbndsend": 0, "secrdmrtgsend": 0, "unsecurednotesend": 0, "retainedearnend": 0, "totnetassetend": 46044589, "nonpfrea": "9", "gftgrntsrcvd170": 0, "txrevnuelevied170": 0, "srvcsval170": 0, "grsinc170": 0, "grsrcptsrelated170": 0, "totgftgrntrcvd509": 3604668, "grsrcptsadmissn509": 61777023, "txrevnuelevied509": 0, "srvcsval509": 0, "subtotsuppinc509": 3078703, "totsupp509": 70441119, "ein": 251191386}, {"tax_prd": 201503, "tax_prd_yr": 2015, "formtype": 0, "pdf_url": "https://projects.propublica.org/nonprofits/download-filing?path=2015_09_EO%2F25-1191386_990_201503.pdf", "updated": "2017-06-30T00:19:31.459Z", "totrevenue": 14495463, "totfuncexpns": 12400594, "totassetsend": 50894345, "totliabend": 5001800, "pct_compnsatncurrofcr": 0.0, "tax_pd": null, "subseccd": 3, "unrelbusinccd": "N", "initiationfees": 0, "grsrcptspublicuse": 0, "grsincmembers": 0, "grsincother": 0, "totcntrbgfts": 114485, "totprgmrevnue": 13761857, "invstmntinc": 596368, "txexmptbndsproceeds": 0, "royaltsinc": 0, "grsrntsreal": 0, "grsrntsprsnl": 0, "rntlexpnsreal": 0, "rntlexpnsprsnl": 0, "rntlincreal": 0, "rntlincprsnl": 0, "netrntlinc": 0, "grsalesecur": 0, "grsalesothr": 60410, "cstbasisecur": 0, "cstbasisothr": 37657, "gnlsecur": 0, "gnlsothr": 22753, "netgnls": 22753, "grsincfndrsng": 0, "lessdirfndrsng": 0, "netincfndrsng": 0, "grsincgaming": 0, "lessdirgaming": 0, "netincgaming": 0, "grsalesinvent": 0, "lesscstofgoods": 0, "netincsales": 0, "miscrevtot11e": 0, "compnsatncurrofcr": 230927, "othrsalwages": 7651874, "payrolltx": 658788, "profndraising": 0, "txexmptbndsend": 0, "secrdmrtgsend": 0, "unsecurednotesend": 0, "retainedearnend": 0, "totnetassetend": 45892545, "nonpfrea": "9", "gftgrntsrcvd170": 0, "txrevnuelevied170": 0, "srvcsval170": 0, "grsinc170": 0, "grsrcptsrelated170": 0, "totgftgrntrcvd509": 3787083, "grsrcptsadmissn509": 60511229, "txrevnuelevied509": 0, "srvcsval509": 0, "subtotsuppinc509": 3042487, "totsupp509": 69142285, "ein": 251191386}, {"tax_prd": 201403, "tax_prd_yr": 2014, "formtype": 0, "pdf_url": "https://projects.propublica.org/nonprofits/download-filing?path=2014_09_EO%2F25-1191386_990_201403.pdf", "updated": "2017-06-30T00:07:15.977Z", "totrevenue": 14226800, "totfuncexpns": 12133615, "totassetsend": 48407844, "totliabend": 1875215, "pct_compnsatncurrofcr": 0.0, "tax_pd": null, "subseccd": 3, "unrelbusinccd": "N", "initiationfees": 0, "grsrcptspublicuse": 0, "grsincmembers": 0, "grsincother": 0, "totcntrbgfts": 40897, "totprgmrevnue": 13545225, "invstmntinc": 635186, "txexmptbndsproceeds": 0, "royaltsinc": 0, "grsrntsreal": 0, "grsrntsprsnl": 0, "rntlexpnsreal": 0, "rntlexpnsprsnl": 0, "rntlincreal": 0, "rntlincprsnl": 0, "netrntlinc": 0, "grsalesecur": 0, "grsalesothr": 8350, "cstbasisecur": 0, "cstbasisothr": 2858, "gnlsecur": 0, "gnlsothr": 5492, "netgnls": 5492, "grsincfndrsng": 0, "lessdirfndrsng": 0, "netincfndrsng": 0, "grsincgaming": 0, "lessdirgaming": 0, "netincgaming": 0, "grsalesinvent": 0, "lesscstofgoods": 0, "netincsales": 0, "miscrevtot11e": 0, "compnsatncurrofcr": 240752, "othrsalwages": 7294673, "payrolltx": 627573, "profndraising": 0, "txexmptbndsend": 0, "secrdmrtgsend": 0, "unsecurednotesend": 0, "retainedearnend": 0, "totnetassetend": 46532629, "nonpfrea": "9", "gftgrntsrcvd170": 0, "txrevnuelevied170": 0, "srvcsval170": 0, "grsinc170": 0, "grsrcptsrelated170": 0, "totgftgrntrcvd509": 3604678, "grsrcptsadmissn509": 58623696, "txrevnuelevied509": 0, "srvcsval509": 0, "subtotsuppinc509": 3033393, "totsupp509": 66940908, "ein": 251191386}, {"tax_prd": 201303, "tax_prd_yr": 2013, "formtype": 0, "pdf_url": "https://projects.propublica.org/nonprofits/download-filing?path=2013_09_EO%2F25-1191386_990_201303.pdf", "updated": "2017-06-29T23:52:06.390Z", "totrevenue": 14005710, "totfuncexpns": 11391034, "totassetsend": 46157950, "totliabend": 2871208, "pct_compnsatncurrofcr": 0.0, "tax_pd": null, "subseccd": 3, "unrelbusinccd": "N", "initiationfees": 0, "grsrcptspublicuse": 0, "grsincmembers": 0, "grsincother": 0, "totcntrbgfts": 74216, "totprgmrevnue": 13281315, "invstmntinc": 650179, "txexmptbndsproceeds": 0, "royaltsinc": 0, "grsrntsreal": 0, "grsrntsprsnl": 0, "rntlexpnsreal": 0, "rntlexpnsprsnl": 0, "rntlincreal": 0, "rntlincprsnl": 0, "netrntlinc": 0, "grsalesecur": 0, "grsalesothr": 0, "cstbasisecur": 0, "cstbasisothr": 0, "gnlsecur": 0, "gnlsothr": 0, "netgnls": 0, "grsincfndrsng": 0, "lessdirfndrsng": 0, "netincfndrsng": 0, "grsincgaming": 0, "lessdirgaming": 0, "netincgaming": 0, "grsalesinvent": 0, "lesscstofgoods": 0, "netincsales": 0, "miscrevtot11e": 0, "compnsatncurrofcr": 210911, "othrsalwages": 6830098, "payrolltx": 570514, "profndraising": 0, "txexmptbndsend": 0, "secrdmrtgsend": 0, "unsecurednotesend": 0, "retainedearnend": 0, "totnetassetend": 43286742, "nonpfrea": "9", "gftgrntsrcvd170": 0, "txrevnuelevied170": 0, "srvcsval170": 0, "grsinc170": 0, "grsrcptsrelated170": 0, "totgftgrntrcvd509": 3550153, "grsrcptsadmissn509": 57530861, "txrevnuelevied509": 0, "srvcsval509": 0, "subtotsuppinc509": 3139695, "totsupp509": 65795749, "ein": 251191386}, {"tax_prd": 201203, "tax_prd_yr": 2012, "formtype": 0, "pdf_url": "https://projects.propublica.org/nonprofits/download-filing?path=2012_11_EO%2F25-1191386_990_201203.pdf", "updated": "2017-06-29T23:38:19.993Z", "totrevenue": 13657600, "totfuncexpns": 11127096, "totassetsend": 42978752, "totliabend": 2631886, "pct_compnsatncurrofcr": 0.0, "tax_pd": null, "subseccd": 3, "unrelbusinccd": "N", "initiationfees": 0, "grsrcptspublicuse": 0, "grsincmembers": 0, "grsincother": 0, "totcntrbgfts": 113377, "totprgmrevnue": 12913376, "invstmntinc": 630847, "txexmptbndsproceeds": 0, "royaltsinc": 0, "grsrntsreal": 0, "grsrntsprsnl": 0, "rntlexpnsreal": 0, "rntlexpnsprsnl": 0, "rntlincreal": 0, "rntlincprsnl": 0, "netrntlinc": 0, "grsalesecur": 0, "grsalesothr": 0, "cstbasisecur": 0, "cstbasisothr": 0, "gnlsecur": 0, "gnlsothr": 0, "netgnls": 0, "grsincfndrsng": 0, "lessdirfndrsng": 0, "netincfndrsng": 0, "grsincgaming": 0, "lessdirgaming": 0, "netincgaming": 0, "grsalesinvent": 0, "lesscstofgoods": 0, "netincsales": 0, "miscrevtot11e": 0, "compnsatncurrofcr": 202257, "othrsalwages": 6621926, "payrolltx": 551590, "profndraising": 0, "txexmptbndsend": 0, "secrdmrtgsend": 0, "unsecurednotesend": 0, "retainedearnend": 0, "totnetassetend": 40346866, "nonpfrea": "9", "gftgrntsrcvd170": 0, "txrevnuelevied170": 0, "srvcsval170": 0, "grsinc170": 0, "grsrcptsrelated170": 0, "totgftgrntrcvd509": 3490292, "grsrcptsadmissn509": 55609242, "txrevnuelevied509": 0, "srvcsval509": 0, "subtotsuppinc509": 3575043, "totsupp509": 64191687, "ein": 251191386}], "filings_without_data": [{"tax_prd": 201103, "tax_prd_yr": 2011, "formtype": 0, "formtype_str": "990", "pdf_url": "https://projects.propublica.org/nonprofits/download-filing?path=2011_09_EO%2F25-1191386_990_201103.pdf"}, {"tax_prd": 201003, "tax_prd_yr": 2010, "formtype": 0, "formtype_str": "990", "pdf_url": "https://projects.propublica.org/nonprofits/download-filing?path=2010_10_EO%2F25-1191386_990_201003.pdf"}, {"tax_prd": 200903, "tax_prd_yr": 2009, "formtype": 0, "formtype_str": "990", "pdf_url": "https://projects.propublica.org/nonprofits/download-filing?path=2009_10_EO%2F25-1191386_990_200903.pdf"}, {"tax_prd": 200803, "tax_prd_yr": 2008, "formtype": 0, "formtype_str": "990", "pdf_url": "https://projects.propublica.org/nonprofits/download-filing?path=2009_01_EO%2F25-1191386_990_200803.pdf"}, {"tax_prd": 200703, "tax_prd_yr": 2007, "formtype": 0, "formtype_str": "990", "pdf_url": "https://projects.propublica.org/nonprofits/download-filing?path=2008_12_EO%2F25-1191386_990_200703.pdf"}, {"tax_prd": 200603, "tax_prd_yr": 2006, "formtype": 0, "formtype_str": "990", "pdf_url": "https://projects.propublica.org/nonprofits/download-filing?path=2006_09_EO%2F25-1191386_990_200603.pdf"}, {"tax_prd": 200503, "tax_prd_yr": 2005, "formtype": 0, "formtype_str": "990", "pdf_url": "https://projects.propublica.org/nonprofits/download-filing?path=2005_10_EO%2F25-1191386_990_200503.pdf"}, {"tax_prd": 200403, "tax_prd_yr": 2004, "formtype": 0, "formtype_str": "990", "pdf_url": "https://projects.propublica.org/nonprofits/download-filing?path=2004_09_EO%2F25-1191386_990_200403.pdf"}, {"tax_prd": 200303, "tax_prd_yr": 2003, "formtype": 0, "formtype_str": "990", "pdf_url": "https://projects.propublica.org/nonprofits/download-filing?path=2003_08_EO%2F25-1191386_990_200303.pdf"}, {"tax_prd": 200203, "tax_prd_yr": 2002, "formtype": 0, "formtype_str": "990", "pdf_url": "https://projects.propublica.org/nonprofits/download-filing?path=2002_09_EO%2F25-1191386_990_200203.pdf"}], "data_source": "ProPublica Nonprofit Explorer API: https://projects.propublica.org/nonprofits/api/\nIRS Exempt Organizations Business Master File Extract (EO BMF): https://www.irs.gov/charities-non-profits/exempt-organizations-business-master-file-extract-eo-bmf\nIRS Annual Extract of Tax-Exempt Organization Financial Data: https://www.irs.gov/uac/soi-tax-stats-annual-extract-of-tax-exempt-organization-financial-data", "api_version": 2}